solve_dde/__init__.py
solve_dde/base.py
solve_dde/common.py
solve_dde/dde.py
solve_dde/rk.py
solve_dde-1.0.1.dist-info/LICENSE
solve_dde-1.0.1.dist-info/METADATA
solve_dde-1.0.1.dist-info/WHEEL
solve_dde-1.0.1.dist-info/top_level.txt
solve_dde-1.0.1.dist-info/RECORD
