Metadata-Version: 2.1
Name: solve-dde
Version: 1.0.1
Summary: Package for solving constant delay differential equations.
Home-page: https://gitlab.com/jrme.jansen/solve_dde
Author: Jerome Jansen
Author-email: jrme.jansen@gmail.com
License: LICENSE
Platform: UNKNOWN
Requires-Dist: matplotlib (==3.1.2)
Requires-Dist: numpy (==1.17.4)
Requires-Dist: scipy (==1.6.0)
